[
    {
        "name":  "Agro TV",
        "logo":  "https://i.imgur.com/MpY41jI.png",
        "website":  "https://www.agrotv.net/",
        "country":  "RS",
        "streams":  [
                        "https://agrotv.streamnet.ro/mobile_tv/agrotv.m3u8",
                        "https://restr2.bgtv.bg/agro/hls/agro.m3u8"
                    ]
    },
    {
        "name":  "Arena Sport 1",
        "logo":  "https://i.imgur.com/RJrJGbW.png",
        "website":  "https://www.tvarenasport.com/",
        "country":  "RS",
        "streams":  "http://91.132.74.5:8000/play/a00k"
    },
    {
        "name":  "Belle Amie",
        "logo":  "https://i.postimg.cc/8k0C7Bbg/belleamie.png",
        "website":  "http://www.belami.rs/",
        "country":  "RS",
        "streams":  "http://92.60.238.10:1935/live/belleamie/playlist.m3u8"
    },
    {
        "name":  "Bloomberg Adria",
        "logo":  "https://i.postimg.cc/FH1873G8/bloombergadria.png",
        "website":  "https://bloombergadria.com/",
        "country":  "RS",
        "streams":  "https://d3ojytvj4doga3.cloudfront.net/app-23764-1566/ngrp:Jq3SvH9h_all/playlist.m3u8"
    },
    {
        "name":  "BTV",
        "logo":  "https://i.imgur.com/jZU9hCg.png",
        "website":  "http://btv.rs/",
        "country":  "RS",
        "streams":  [
                        "https://btv.secureswiftcontent.com/han/btv/btv10005/srtoutput/manifest.m3u8",
                        "https://fs3.kabelko.sk/9011/index.m3u8?token=btv",
                        "https://streamfi-alphadgtl1.zettawiseroutes.com:8181/hls/stream.m3u8"
                    ]
    },
    {
        "name":  "DM Sat",
        "logo":  "https://i.postimg.cc/K8b9XWHZ/dmsat.png",
        "website":  "http://www.dmsat.tv/",
        "country":  "RS",
        "streams":  [
                        "https://viamotionhsi.netplus.ch/live/eds/dmsat/browser-dash/dmsat.mpd",
                        "https://viamotionhsi.netplus.ch/live/eds/dmsat/browser-HLS8/dmsat.m3u8"
                    ]
    },
    {
        "name":  "EDU TV",
        "logo":  "https://i.postimg.cc/XJ2MXbtc/edutv.png",
        "website":  "http://www.edutelevision.com/",
        "country":  "RS",
        "streams":  "https://5aa64ca8b95b8.streamlock.net:4443/edutv/edutelevizija/playlist.m3u8"
    },
    {
        "name":  "ELECTRO",
        "logo":  "https://i.imgur.com/9dz8MsD.png",
        "website":  "https://www.muzzik.tv/",
        "country":  "RS",
        "streams":  "https://muzzik-live.morescreens.com/mts-9/playlist.m3u8"
    },
    {
        "name":  "Euronews Serbia",
        "logo":  "https://i.postimg.cc/3J0RMSDb/euronewsserbia.png",
        "website":  "https://www.euronews.rs/",
        "country":  "RS",
        "streams":  "https://d1ei8ofhgfmkac.cloudfront.net/app-19518-1306/ngrp:QoZfNjsg_all/playlist.m3u8"
    },
    {
        "name":  "FLASHBACK",
        "logo":  "https://i.imgur.com/9dz8MsD.png",
        "website":  "https://www.muzzik.tv/",
        "country":  "RS",
        "streams":  "https://muzzik-live.morescreens.com/mts-8/playlist.m3u8"
    },
    {
        "name":  "Fortuna TV",
        "logo":  "https://i.imgur.com/gwBELFt.png",
        "website":  "http://www.rtvfortuna.com/",
        "country":  "RS",
        "streams":  [
                        "https://edge1.socialsmart.tv/ftvturk/bant1/playlist.m3u8",
                        "https://streamtv.intervenhosting.net:3355/live/fortunatvlive.m3u8"
                    ]
    },
    {
        "name":  "JEKA",
        "logo":  "https://i.postimg.cc/SNqhVmpd/jeka.png",
        "website":  "https://www.muzzik.tv/",
        "country":  "RS",
        "streams":  "https://muzzik-live.morescreens.com/mts-4/playlist.m3u8"
    },
    {
        "name":  "K1",
        "logo":  "https://i.imgur.com/U3wXj5k.png",
        "website":  "http://k1tv.rs/",
        "country":  "RS",
        "streams":  "https://edge2.iptv.macc.com.ua/life/k1_2/index.m3u8"
    },
    {
        "name":  "Kurir TV",
        "logo":  "https://i.imgur.com/HBPnUD5.png",
        "website":  "https://www.kurir.rs/",
        "country":  "RS",
        "streams":  "https://kurir-tv.haste-cdn.net/providus/live2805.m3u8"
    },
    {
        "name":  "LOL",
        "logo":  "https://i.postimg.cc/9XyvSsmf/lol.png",
        "website":  "http://www.pink.rs/lol",
        "country":  "RS",
        "streams":  "https://origin3.afxp.telemedia.co.za/PremiumFree/lol/playlist.m3u8"
    },
    {
        "name":  "MOBA",
        "logo":  "https://i.imgur.com/9dz8MsD.png",
        "website":  "https://www.muzzik.tv/",
        "country":  "RS",
        "streams":  "https://muzzik-live.morescreens.com/mts-2/playlist.m3u8"
    },
    {
        "name":  "MUZZIK",
        "logo":  "https://i.imgur.com/9dz8MsD.png",
        "website":  "https://www.muzzik.tv/",
        "country":  "RS",
        "streams":  "https://muzzik-live.morescreens.com/mts-6/playlist.m3u8"
    },
    {
        "name":  "Narodna TV",
        "logo":  "https://i.postimg.cc/fRrHBCQf/narodnatv.png",
        "website":  "https://pinkmediagroup.net/",
        "country":  "RS",
        "streams":  "https://edge8.pink.rs/narodnatv/index.m3u8"
    },
    {
        "name":  "National Geographic",
        "logo":  "https://upload.wikimedia.org/wikipedia/commons/thumb/f/fc/Natgeologo.svg/512px-Natgeologo.svg.png",
        "website":  "https://nationalgeographic.rs/",
        "country":  "RS",
        "streams":  [
                        "http://62.210.211.188:2095/play/a00d",
                        "http://78.130.250.2:8023/play/a02e/index.m3u8",
                        "https://saran-live.ercdn.net/natgeohd/index.m3u8"
                    ]
    },
    {
        "name":  "National Geographic Wild",
        "logo":  "https://upload.wikimedia.org/wikipedia/commons/thumb/2/27/National_Geographic_Wild_logo.svg/512px-National_Geographic_Wild_logo.svg.png",
        "website":  "https://www.natgeotv.com/rs",
        "country":  "RS",
        "streams":  [
                        "http://78.130.250.2:8023/play/a02c/index.m3u8",
                        "https://saran-live.ercdn.net/natgeowild/index.m3u8"
                    ]
    },
    {
        "name":  "Nickelodeon",
        "logo":  "https://upload.wikimedia.org/wikipedia/commons/thumb/7/7a/Nickelodeon_2009_logo.svg/512px-Nickelodeon_2009_logo.svg.png",
        "website":  "http://www.nick.tv/",
        "country":  "RS",
        "streams":  [
                        "http://185.236.229.62:9981/play/a067",
                        "http://195.64.140.147:10121/121",
                        "http://23.237.104.106:8080/USA_NICKELODEON/index.m3u8",
                        "http://46.8.46.14/Nickelodeon/index.m3u8",
                        "http://87.246.60.6:11004/?token=fas-tv.com",
                        "http://92.114.85.72:8000/play/a02o",
                        "https://ma.anixa.tv/clips/stream/nickelodeon/playlist.php"
                    ]
    },
    {
        "name":  "Nisville TV",
        "logo":  "https://i.imgur.com/cbtgd2h.png",
        "website":  "http://nisville.com/",
        "country":  "RS",
        "streams":  "https://tv.nisville.com/live/nisville/playlist.m3u8"
    },
    {
        "name":  "Nova",
        "logo":  "https://i.imgur.com/sU8UPPY.png",
        "website":  "https://nova.rs/",
        "country":  "RS",
        "streams":  "http://176.65.146.237:8401/play/a0ah/index.m3u8"
    },
    {
        "name":  "Nova TV",
        "logo":  "https://i.imgur.com/hA9O8Bv.png",
        "website":  "https://www.novatv.rs/",
        "country":  "RS",
        "streams":  "http://91.132.74.5:8000/play/a005"
    },
    {
        "name":  "NTV",
        "logo":  "https://i.imgur.com/xNf4l8u.png",
        "website":  "https://novosadska.tv/",
        "country":  "RS",
        "streams":  [
                        "http://43.252.18.195:5080/LiveApp/streams/ntvhd.m3u8",
                        "https://cdn4.skygo.mn/live/disk1/NTVHD/DASH-FTA/NTVHD.mpd",
                        "https://cdn4.skygo.mn/live/disk1/NTVHD/HLSv3-FTA/NTVHD.m3u8",
                        "https://dogus-live.daioncdn.net/ntv/ntv.m3u8",
                        "https://live-evg10.tv360.metfone.com.kh/LiveApp/streams/ntvhd.m3u8",
                        "https://panel.miplay.cl:8082/ntv/index.m3u8",
                        "https://s-pl-01.mediatool.tv/playout/ntv-abr/index.m3u8"
                    ]
    },
    {
        "name":  "Pannon TV",
        "logo":  "https://i.imgur.com/xQa2idL.png",
        "website":  "https://pannonrtv.com/",
        "country":  "RS",
        "streams":  "https://stream.nmih.hu:4102/live.m3u8"
    },
    {
        "name":  "Pink",
        "logo":  "https://i.imgur.com/66wHb7E.png",
        "website":  "http://www.rtvpink.co.rs/",
        "country":  "RS",
        "streams":  [
                        "https://edge8.pink.rs/pinktv/index.m3u8",
                        "https://live.rednet.rs/providus/pink1.m3u8"
                    ]
    },
    {
        "name":  "POP STAR",
        "logo":  "https://i.imgur.com/E9ha9Or.png",
        "website":  "https://muzzik.co.uk/",
        "country":  "RS",
        "streams":  "https://muzzik-live.morescreens.com/mts-3/playlist.m3u8"
    },
    {
        "name":  "Radio Hit FM TV",
        "logo":  "https://i.imgur.com/gP2OT4S.png",
        "website":  "http://www.hitfm.rs/",
        "country":  "RS",
        "streams":  "https://peer2.tdiradio.com/static/streaming-playlists/hls/bab99862-ec1c-474f-9a02-4f8c8677d565/0.m3u8"
    },
    {
        "name":  "Radio Karolina TV",
        "logo":  "https://i.imgur.com/g2HpLX1.png",
        "website":  "http://www.karolina.rs/",
        "country":  "RS",
        "streams":  "https://peer2.tdiradio.com/static/streaming-playlists/hls/4207de1d-52e8-4591-ad9e-218069b864d1/0.m3u8"
    },
    {
        "name":  "Radio Lola TV",
        "logo":  "https://i.imgur.com/41eE8fl.png",
        "website":  "http://www.karolina.rs/",
        "country":  "RS",
        "streams":  "https://peer2.tdiradio.com/static/streaming-playlists/hls/7c3ea8d3-49dc-4e1b-8b1e-dc6fab71f5cf/0.m3u8"
    },
    {
        "name":  "Red TV",
        "logo":  "https://i.postimg.cc/XvpfhZ50/redtv.png",
        "website":  "https://redportal.rs/",
        "country":  "RS",
        "streams":  [
                        "https://live.rednet.rs/providus/redtv_multi.m3u8",
                        "https://live.rednet.rs/providus/redtv_multi_hq/index.m3u8"
                    ]
    },
    {
        "name":  "Rock\u0026Roll",
        "logo":  "https://i.imgur.com/sy1BDNK.png",
        "website":  "https://www.muzzik.tv/",
        "country":  "RS",
        "streams":  "https://muzzik-live.morescreens.com/mts-1/playlist.m3u8"
    },
    {
        "name":  "RTP",
        "logo":  "https://i.imgur.com/v8QovqI.png",
        "website":  "http://www.rtp.rs/",
        "country":  "RS",
        "streams":  [
                        "https://flash2.xdevel.com/rtptv/rtptv/playlist.m3u8",
                        "https://rtp.noxun.net/hls/stream.m3u8"
                    ]
    },
    {
        "name":  "RTS 1",
        "logo":  "https://i.postimg.cc/WzXmC05T/rts1.png",
        "website":  "http://www.rts.rs/page/tv/sr/news/20/rts-1.html",
        "country":  "RS",
        "streams":  "https://webtvstream.bhtelecom.ba/rts1.m3u8"
    },
    {
        "name":  "RTS 2",
        "logo":  "https://i.postimg.cc/mZwSPGBJ/rts2.png",
        "website":  "http://www.rts.rs/page/tv/sr/news/21/rts-2.html",
        "country":  "RS",
        "streams":  "https://webtvstream.bhtelecom.ba/rts2.m3u8"
    },
    {
        "name":  "RTS 3",
        "logo":  "https://i.postimg.cc/fTRfXgbL/rts3.png",
        "website":  "http://www.rts.rs/page/tv/sr/news/255/rts-3.html",
        "country":  "RS",
        "streams":  "https://uvotv-aniview.global.ssl.fastly.net/hls/live/2120431/rts3/playlist.m3u8"
    },
    {
        "name":  "RTS Svet",
        "logo":  "https://i.postimg.cc/vmv4Gq8W/rtssvet.png",
        "website":  "http://www.rts.rs/page/tv/sr/news/22/rts-svet.html",
        "country":  "RS",
        "streams":  [
                        "https://viamotionhsi.netplus.ch/live/eds/rtssat/browser-dash/rtssat.mpd",
                        "https://viamotionhsi.netplus.ch/live/eds/rtssat/browser-HLS8/rtssat.m3u8"
                    ]
    },
    {
        "name":  "RTV 1",
        "logo":  "https://i.imgur.com/CG44YT3.png",
        "website":  "https://www.rtv.rs/",
        "country":  "RS",
        "streams":  [
                        "mmsh://212.200.255.151/rtv1",
                        "rtsp://212.200.255.151/rtv1"
                    ]
    },
    {
        "name":  "RTV 2",
        "logo":  "https://i.postimg.cc/rm3HdXSv/rtv2.png",
        "website":  "https://www.rtv.rs/",
        "country":  "RS",
        "streams":  [
                        "mmsh://212.200.255.151/rtv2",
                        "rtsp://212.200.255.151/rtv2"
                    ]
    },
    {
        "name":  "RTV Bap",
        "logo":  "https://i.imgur.com/TBAtPH6.png",
        "website":  "http://www.rtvbap.rs/",
        "country":  "RS",
        "streams":  "https://53be5ef2d13aa.streamlock.net/rtvbap/uzivo/playlist.m3u8"
    },
    {
        "name":  "RTV Novi Pazar",
        "logo":  "https://i.imgur.com/NpyRVyC.png",
        "website":  "https://rtvnp.rs/",
        "country":  "RS",
        "streams":  "https://hls.rtvnp.rs/tvlive/75e168bf8304fe9b1fac9a6c2f702d590e1cf986.m3u8"
    },
    {
        "name":  "Sandzak TV",
        "logo":  "https://i.imgur.com/lm9Fgsp.png",
        "website":  "http://www.sandzak.tv/",
        "country":  "RS",
        "streams":  "https://streaming.iptv.nextfiber.rs/nxt004/master.m3u8"
    },
    {
        "name":  "SENSE",
        "logo":  "https://i.imgur.com/9dz8MsD.png",
        "website":  "https://muzzik.co.uk/",
        "country":  "RS",
        "streams":  "https://muzzik-live.morescreens.com/mts-7/playlist.m3u8"
    },
    {
        "name":  "SOS Kanal Plus",
        "logo":  "https://i.postimg.cc/G3zztsCv/soskanalplus.png",
        "website":  "https://www.soskanal.net/",
        "country":  "RS",
        "streams":  "https://53be5ef2d13aa.streamlock.net/soskanalplus/soskanalplus.stream/playlist.m3u8"
    },
    {
        "name":  "TDI Radio TV",
        "logo":  "https://i.imgur.com/POdTmaD.png",
        "website":  "http://www.tdiradio.com/",
        "country":  "RS",
        "streams":  "https://peer2.tdiradio.com/static/streaming-playlists/hls/8f5d84ce-e8ac-4109-9975-9665f5605557/master.m3u8"
    },
    {
        "name":  "TIKTAK",
        "logo":  "https://i.imgur.com/9dz8MsD.png",
        "website":  "https://www.muzzik.tv/",
        "country":  "RS",
        "streams":  "https://muzzik-live.morescreens.com/mts-a5/playlist.m3u8"
    },
    {
        "name":  "Top TV",
        "logo":  "https://i.imgur.com/UJqbKEC.png",
        "website":  "http://www.top-tv.rs/",
        "country":  "RS",
        "streams":  "http://82.165.71.58:8081/TopTV/live/playlist.m3u8"
    },
    {
        "name":  "TV AS",
        "logo":  "https://i.imgur.com/LIUtEgD.png",
        "website":  "http://www.rtvas.rs/",
        "country":  "RS",
        "streams":  "https://srv1.adriatelekom.com/TVAS/index.m3u8"
    },
    {
        "name":  "TV Duga+",
        "logo":  "https://i.postimg.cc/mktbvRg5/tvdugaplus.png",
        "website":  "http://www.tvdugaplus.com/",
        "country":  "RS",
        "streams":  "http://109.92.29.10:1935/tvduga/tvduga/playlist.m3u8"
    },
    {
        "name":  "TV Hram",
        "logo":  "https://i.postimg.cc/Dzn721zs/tvhram.png",
        "website":  "http://www.tvhram.rs/",
        "country":  "RS",
        "streams":  "https://vod1.laki.eu/live/hram/index.m3u8"
    },
    {
        "name":  "TV Kanal M",
        "logo":  "https://i.imgur.com/hqNVRUU.png",
        "website":  "http://www.rtvparacin.rs/",
        "country":  "RS",
        "streams":  "http://176.67.210.1/hls/kanalm.m3u8"
    },
    {
        "name":  "TV Marsh",
        "logo":  "https://i.imgur.com/Dt1mPyX.png",
        "website":  "http://marsh.rs/",
        "country":  "RS",
        "streams":  "http://cdn.dovecher.tv:8081/live/marsh/playlist.m3u8"
    },
    {
        "name":  "TV Pi Kanal",
        "logo":  "https://i.imgur.com/8ugnFa3.png",
        "website":  "http://www.rtvpicanal.com/",
        "country":  "RS",
        "streams":  "https://stream.pikanal.rs/pikanal/pgm.m3u8"
    },
    {
        "name":  "TV Pirot",
        "logo":  "https://i.imgur.com/o5y1ok6.png",
        "website":  null,
        "country":  "RS",
        "streams":  "https://5bc45691ca49f.streamlock.net/tvpirot/uzivo/playlist.m3u8"
    },
    {
        "name":  "VTV",
        "logo":  "https://i.imgur.com/7jCHU4c.png",
        "website":  "http://www.novosadska.tv/",
        "country":  "RS",
        "streams":  [
                        "https://d3q93l5bumjyoq.cloudfront.net/index.m3u8",
                        "https://vtvstream.vnews.mv/vtvlive/vmedia/playlist.m3u8"
                    ]
    },
    {
        "name":  "WORLD WIDE MUZZIK",
        "logo":  "https://i.imgur.com/tEzppGC.png",
        "website":  "https://muzzik.co.uk/",
        "country":  "RS",
        "streams":  "https://muzzik-live.morescreens.com/mts-5/playlist.m3u8"
    },
    {
        "name":  "ZZ TV",
        "logo":  "https://i.imgur.com/9dz8MsD.png",
        "website":  "https://muzzik.co.uk/",
        "country":  "RS",
        "streams":  "https://muzzik-live.morescreens.com/mts-a4/playlist.m3u8"
    }
]
